webl/__init__.py
webl/cli.py
webl/client.py
webl/config.py
webl/formatter.py
webl-0.2.0.dist-info/LICENSE
webl-0.2.0.dist-info/METADATA
webl-0.2.0.dist-info/WHEEL
webl-0.2.0.dist-info/entry_points.txt
webl-0.2.0.dist-info/top_level.txt
webl-0.2.0.dist-info/RECORD
