Metadata-Version: 2.1
Name: webl
Version: 0.2.0
Summary: Command-line tool for domain intelligence and authority lookups
Home-page: https://github.com/websitelaunches/webl-cli
Author: Website Launches
Author-email: support@websitelaunches.com
Classifier: Development Status :: 4 - Beta
Classifier: Intended Audience :: Developers
Classifier: Topic :: Internet :: WWW/HTTP
Classifier: Topic :: System :: Networking
Classifier: License :: OSI Approved :: MIT License
Classifier: Programming Language :: Python :: 3
Classifier: Programming Language :: Python :: 3.7
Classifier: Programming Language :: Python :: 3.8
Classifier: Programming Language :: Python :: 3.9
Classifier: Programming Language :: Python :: 3.10
Classifier: Programming Language :: Python :: 3.11
Requires-Python: >=3.7
License-File: LICENSE
Requires-Dist: click >=8.0.0
Requires-Dist: requests >=2.28.0
Requires-Dist: rich >=13.0.0
